isannlp/__init__.py
isannlp/corpus/__init__.py
isannlp/corpus/korat_listword.txt
isannlp/corpus/korat_words.md
isannlp/corpus/nangrong_words.md
isannlp/corpus/nangrong_words.txt
isannlp/tokenize/__init__.py
IsanNLP-0.1.dev2.dist-info/LICENSE
IsanNLP-0.1.dev2.dist-info/METADATA
IsanNLP-0.1.dev2.dist-info/WHEEL
IsanNLP-0.1.dev2.dist-info/top_level.txt
IsanNLP-0.1.dev2.dist-info/RECORD
