Metadata-Version: 2.1
Name: IsanNLP
Version: 0.1.dev2
Summary: Isan Natural Language Processing library
Home-page: https://github.com/wannaphongcom/IsanNLP
Author: wannaphong
Author-email: wannaphong@yahoo.com
License-File: LICENSE
Requires-Dist: pythainlp
